LICENSE
MANIFEST.in
README.rst
setup.py
bootstrap5form/__init__.py
bootstrap5form/config.py
bootstrap5form/meta.py
bootstrap5form/models.py
bootstrap5form/tests.py
bootstrap5form/templates/bootstrap5form/field.html
bootstrap5form/templates/bootstrap5form/form.html
bootstrap5form/templates/bootstrap5form/formset.html
bootstrap5form/templatetags/__init__.py
bootstrap5form/templatetags/bootstrap5form.py
django_bootstrap5_form.egg-info/PKG-INFO
django_bootstrap5_form.egg-info/SOURCES.txt
django_bootstrap5_form.egg-info/dependency_links.txt
django_bootstrap5_form.egg-info/not-zip-safe
django_bootstrap5_form.egg-info/requires.txt
django_bootstrap5_form.egg-info/top_level.txt
tests/test_settings.py