Metadata-Version: 2.1
Name: django-bootstrap5-form
Version: 5.0.2
Summary: django-bootstrap5-form
Home-page: http://github.com/gwasser/django-bootstrap5-form
Author: gwasser
Author-email: gwasser+github@gmail.com
License: MIT
Keywords: bootstrap5,django
Classifier: Programming Language :: Python
Classifier: Topic :: Software Development :: Libraries :: Python Modules
Classifier: Framework :: Django
Classifier: Framework :: Django :: 3.0
Classifier: Framework :: Django :: 3.1
Classifier: Framework :: Django :: 3.2
Classifier: Environment :: Web Environment
Classifier: Programming Language :: Python :: 3
Classifier: Programming Language :: Python :: 3.8
Classifier: Programming Language :: Python :: 3.9
Classifier: Programming Language :: Python :: 3.10
Classifier: Programming Language :: Python :: 3.11
Classifier: Programming Language :: Python :: 3.12
License-File: LICENSE
Requires-Dist: django<4,>=3
